{
    "ar": "رماح",
    "bg": "Копия",
    "cs": "Oštěpy",
    "da": "Spyd",
    "de": "Speere",
    "el": "Δόρατα",
    "en": "Spears",
    "es": "Lanzas",
    "es-419": "Lanzas",
    "fi": "Keihäät",
    "fr": "Lances",
    "hu": "Dárdák",
    "it": "Lance",
    "ja": "槍",
    "ko": "창",
    "nl": "Spiesen",
    "no": "Spyd",
    "pl": "Włócznie",
    "pt": "Lanças",
    "pt-BR": "Lanças",
    "ro": "Sulițe",
    "ru": "Копья",
    "sv": "Spjut",
    "th": "หอก",
    "tr": "Mızraklar",
    "uk": "Списи",
    "vi": "Giáo",
    "zh-CN": "矛",
    "zh-TW": "矛"
}
