{
    "ar": "خوذة شائكة",
    "bg": "Бодлив шлем",
    "cs": "Trnitá helma",
    "da": "Tornet hjelm",
    "de": "Dorniger Helm",
    "el": "Αγκιστρωτό κράνος",
    "en": "Spiny Helm",
    "es": "Yelmo espinoso",
    "es-419": "Yelmo espinoso",
    "fi": "Piikikäs kypärä",
    "fr": "Heaume épineux",
    "hu": "Tüskés sisak",
    "it": "Elmo spinoso",
    "ja": "スパイニーヘルム",
    "ko": "가시 투구",
    "nl": "Stekelige helm",
    "no": "Pigget hjelm",
    "pl": "Kolczasty hełm",
    "pt": "Elmo espinhoso",
    "pt-BR": "Elmo espinhoso",
    "ro": "Coif țepos",
    "ru": "Шипастый шлем",
    "sv": "Taggig hjälm",
    "th": "หมวกเกราะหนาม",
    "tr": "Dikenli Miğfer",
    "uk": "Шолом з колючками",
    "vi": "Mũ bảo hiểm có gai",
    "zh-CN": "多刺头盔",
    "zh-TW": "多刺頭盔"
}
